ezface/__init__.py
ezface/face_recognition.py
ezface-0.0.1.dist-info/LICENSE
ezface-0.0.1.dist-info/METADATA
ezface-0.0.1.dist-info/WHEEL
ezface-0.0.1.dist-info/top_level.txt
ezface-0.0.1.dist-info/RECORD
