Metadata-Version: 2.1
Name: ezface
Version: 0.0.1
Summary: This project provides an easy way to recognize faces using AI
Home-page: https://github.com/sunjian-github/ezface
Author: SunJian
Author-email: 330160114@qq.com
License-File: LICENSE
